oatlib/__init__.py
oatlib/method.py
oatlib/oat_algorithms.py
oatlib/oat_utils.py
oatlib/sensor.py
oatlib/sos2sos.py
oatlib-0.0.17.dist-info/LICENSE
oatlib-0.0.17.dist-info/METADATA
oatlib-0.0.17.dist-info/WHEEL
oatlib-0.0.17.dist-info/top_level.txt
oatlib-0.0.17.dist-info/zip-safe
oatlib-0.0.17.dist-info/RECORD
