Metadata-Version: 2.1
Name: oatlib
Version: 0.0.17
Summary: Observation Analysis Tool: library to handle time series
Home-page: https://gitlab.com/ist-supsi/OAT
Author: Massimiliano Cannata
Author-email: massimiliano.cannata@gmail.com
License: GPLv2+
Keywords: example,setuptools
Classifier: License :: OSI Approved :: GNU General Public License v2 or later (GPLv2+)
Classifier: Programming Language :: Python :: 3
License-File: LICENSE
Requires-Dist: datetime
Requires-Dist: dateutils
Requires-Dist: pandas
Requires-Dist: numpy
Requires-Dist: scipy
Requires-Dist: requests
Requires-Dist: spatialite
Requires-Dist: isodate
